brotli-stubs/__init__.pyi
brotli_stubs-1.1.0.dist-info/WHEEL
brotli_stubs-1.1.0.dist-info/METADATA
brotli_stubs-1.1.0.dist-info/RECORD
