Metadata-Version: 2.3
Name: brotli-stubs
Version: 1.1.0
Summary: Type stubs for the brotli library
Author: Thomas Carroll
Author-email: Thomas Carroll <tcarroll@snufk.in>
License: MIT License
Classifier: License :: OSI Approved :: MIT License
Classifier: Programming Language :: Python :: 3
Classifier: Typing :: Stubs Only
Requires-Dist: brotli==1.1.0
Requires-Python: >=3.8
